etypes/__init__.py
etypes/ansible/loader.py
etypes/auto_loader.py
etypes/cli/etypes.py
etypes/etypes.py
etypes/exceptions.py
etypes/helpers.py
etypes/processor.py
etypes/utils.py
etypes-1.0.4.dist-info/METADATA
etypes-1.0.4.dist-info/WHEEL
etypes-1.0.4.dist-info/entry_points.txt
etypes-1.0.4.dist-info/RECORD
